Metadata-Version: 1.0
Name: django-singletons
Version: 0.1.5
Summary: Reusable singleton models for Django
Home-page: http://github.com/tttallis/django-singletons
Author: Thomas Ashelford
Author-email: thomas@ether.com.au
License: UNKNOWN
Platform: UNKNOWN
Classifier: Development Status :: 4 - Beta
Classifier: Environment :: Web Environment
Classifier: Intended Audience :: Developers
Classifier: License :: OSI Approved :: BSD License
Classifier: Operating System :: OS Independent
Classifier: Programming Language :: Python
Classifier: Framework :: Django
